CHANGES.txt
LICENSE.txt
MANIFEST.in
README.txt
bootstrap.py
buildout.cfg
setup.py
src/j01/__init__.py
src/j01.scroller.egg-info/PKG-INFO
src/j01.scroller.egg-info/SOURCES.txt
src/j01.scroller.egg-info/dependency_links.txt
src/j01.scroller.egg-info/namespace_packages.txt
src/j01.scroller.egg-info/not-zip-safe
src/j01.scroller.egg-info/requires.txt
src/j01.scroller.egg-info/top_level.txt
src/j01/scroller/README.txt
src/j01/scroller/__init__.py
src/j01/scroller/browser.py
src/j01/scroller/custom.py
src/j01/scroller/jsonrpc.py
src/j01/scroller/simple.py
src/j01/scroller/source.txt
src/j01/scroller/source_MIGRATION_P2P3.py
src/j01/scroller/tests.py
src/j01/scroller/img/mCSB_buttons.png
src/j01/scroller/js/j01.scroller.js
src/j01/scroller/js/j01.simplescroller.js
src/j01/scroller/js/jquery.mCustomScrollbar.js
src/j01/scroller/js/jquery.mousewheel.js
src/j01/scroller/js/jquery.nanoscroller.js
src/j01/scroller/less/jquery.mCustomScrollbar.less
src/j01/scroller/less/jquery.nanoscroller.less